pyproject.toml
setup.py
fotoviewer/__init__.py
fotoviewer/get_token.py
fotoviewer/parse_emls.py
fotoviewer/read_exif.py
fotoviewer/read_mailbox.py
fotoviewer/update_app.py
fotoviewer.egg-info/PKG-INFO
fotoviewer.egg-info/SOURCES.txt
fotoviewer.egg-info/dependency_links.txt
fotoviewer.egg-info/requires.txt
fotoviewer.egg-info/top_level.txt
fotoviewer.egg-info/zip-safe