Metadata-Version: 2.1
Name: fotoviewer
Version: 2024.9.1
Summary: Converteren van breslocaties naar bresvlakken
Author-email: Daniel Tollenaar <daniel@d2hydro.nl>
License: MIT
Project-URL: Source, https://github.com/d2hydro/fotoviewer
Requires-Python: <3.13,>3.7
Requires-Dist: bs4
Requires-Dist: geopandas
Requires-Dist: msal
Requires-Dist: pyogrio
Requires-Dist: pillow
